sonoff_ewelink_cube_client_api/__init__.py
sonoff_ewelink_cube_client_api/api/__init__.py
sonoff_ewelink_cube_client_api/api/baseClass.py
sonoff_ewelink_cube_client_api/api/baseClassBridge.py
sonoff_ewelink_cube_client_api/api/baseClassDevice.py
sonoff_ewelink_cube_client_api/api/baseClassHardware.py
sonoff_ewelink_cube_client_api/api/baseClassSse.py
sonoff_ewelink_cube_client_api/api/ihostClass.py
sonoff_ewelink_cube_client_api/api/nspanelproClass.py
sonoff_ewelink_cube_client_api/config/__init__.py
sonoff_ewelink_cube_client_api/ts/__init__.py
sonoff_ewelink_cube_client_api/ts/enum/ECapability.py
sonoff_ewelink_cube_client_api/ts/enum/ECategory.py
sonoff_ewelink_cube_client_api/ts/enum/EMethod.py
sonoff_ewelink_cube_client_api/ts/enum/EPath.py
sonoff_ewelink_cube_client_api/ts/enum/__init__.py
sonoff_ewelink_cube_client_api/ts/interface/IConfig.py
sonoff_ewelink_cube_client_api/ts/interface/IDebugLog.py
sonoff_ewelink_cube_client_api/ts/interface/IDevice.py
sonoff_ewelink_cube_client_api/ts/interface/IHttpConfig.py
sonoff_ewelink_cube_client_api/ts/interface/IResponse.py
sonoff_ewelink_cube_client_api/ts/interface/ISseEvent.py
sonoff_ewelink_cube_client_api/ts/interface/IThirdParty.py
sonoff_ewelink_cube_client_api/ts/interface/IThirdpartyDevice.py
sonoff_ewelink_cube_client_api/ts/interface/__init__.py
sonoff_ewelink_cube_client_api/utils/__init__.py
sonoff_ewelink_cube_client_api/utils/eventsource.py
sonoff_ewelink_cube_client_api/utils/httpUtils.py
sonoff_ewelink_cube_client_api-0.0.2.dist-info/LICENSE
sonoff_ewelink_cube_client_api-0.0.2.dist-info/METADATA
sonoff_ewelink_cube_client_api-0.0.2.dist-info/WHEEL
sonoff_ewelink_cube_client_api-0.0.2.dist-info/top_level.txt
sonoff_ewelink_cube_client_api-0.0.2.dist-info/RECORD
