Metadata-Version: 2.1
Name: sonoff-ewelink-cube-client-api
Version: 0.0.2
Summary: SONOFF eWelink CUBE API communication library (unofficial)
Home-page: https://github.com/sm4rth0m3/python-pip.sonoff-ewelink-cube-client-api
Author: sipimokus
Author-email: sipimokus@gmail.com
Project-URL: Bug Tracker, https://github.com/sm4rth0m3/python-pip.sonoff-ewelink-cube-client-api/issues
Project-URL: Documentation, https://github.com/sm4rth0m3/python-pip.sonoff-ewelink-cube-client-api
Keywords: sonoff ewelink cube api openapi ihost nspanel library asyncio
Classifier: Development Status :: 3 - Alpha
Classifier: Intended Audience :: Developers
Classifier: License :: OSI Approved :: MIT License
Classifier: Operating System :: OS Independent
Classifier: Programming Language :: Python :: 3
Classifier: Topic :: Home Automation
Classifier: Topic :: Software Development :: Libraries :: Python Modules
Classifier: Topic :: System :: Networking
Classifier: Topic :: Utilities
Requires-Python: >=3.6
License-File: LICENSE
Requires-Dist: aiohttp (>=3.0.0)
Requires-Dist: asyncio (>=3.4.3)
Requires-Dist: setuptools
